django_admin_relation_links/__init__.py
django_admin_relation_links/models.py
django_admin_relation_links/options.py
django_admin_relation_links-0.2.0.dist-info/DESCRIPTION.rst
django_admin_relation_links-0.2.0.dist-info/METADATA
django_admin_relation_links-0.2.0.dist-info/RECORD
django_admin_relation_links-0.2.0.dist-info/WHEEL
django_admin_relation_links-0.2.0.dist-info/metadata.json
django_admin_relation_links-0.2.0.dist-info/top_level.txt
